Metadata-Version: 2.1
Name: cprep
Version: 0.1.13
Summary: Preparing contests made easy
Home-page: https://github.com/bicsi/testutil
Author: Stephen Hudson
Author-email: bicsi@ymail.com
License: GNU General Public License
Platform: UNKNOWN
Classifier: Development Status :: 1 - Planning
Classifier: License :: OSI Approved :: MIT License
Classifier: Operating System :: OS Independent
Classifier: Programming Language :: Python :: 3
Requires-Python: >=3.6
